setup.py
devashish_probability/Binomialdistribution.py
devashish_probability/Gaussiandistribution.py
devashish_probability/Generaldistribution.py
devashish_probability/__init__.py
devashish_probability.egg-info/PKG-INFO
devashish_probability.egg-info/SOURCES.txt
devashish_probability.egg-info/dependency_links.txt
devashish_probability.egg-info/not-zip-safe
devashish_probability.egg-info/top_level.txt