Metadata-Version: 1.0
Name: devashish-probability
Version: 0.2
Summary: Gaussian distributions and Binomial Distributions
Home-page: UNKNOWN
Author: Devashish Shivmurthy
Author-email: devashish.shivmurthy@gmail.com
License: UNKNOWN
Platform: UNKNOWN
